basic_shopify_api/__init__.py
basic_shopify_api/__version__.py
basic_shopify_api/constants.py
basic_shopify_api/deferrer.py
basic_shopify_api/models.py
basic_shopify_api/options.py
basic_shopify_api/store.py
basic_shopify_api/types.py
basic_shopify_api/utils.py
basic_shopify_api/clients/__init__.py
basic_shopify_api/clients/async_client.py
basic_shopify_api/clients/client.py
basic_shopify_api/clients/common.py
basic_shopify_api-1.0.1.dist-info/LICENSE
basic_shopify_api-1.0.1.dist-info/METADATA
basic_shopify_api-1.0.1.dist-info/WHEEL
basic_shopify_api-1.0.1.dist-info/top_level.txt
basic_shopify_api-1.0.1.dist-info/RECORD
