Metadata-Version: 2.1
Name: basic-shopify-api
Version: 1.0.1
Summary: A sync/async REST and GraphQL client for Shopify API using HTTPX
Home-page: https://github.com/osiset/basic_shopify_api
Author: osiset
Author-email: tyler@osiset.com
License: MIT License
Platform: Any
Requires-Python: >=3.6
Requires-Dist: httpx (>=0.13)
